file_ls/__init__.py
file_ls/file_management.py
file_ls-1.0.1.dist-info/METADATA
file_ls-1.0.1.dist-info/WHEEL
file_ls-1.0.1.dist-info/top_level.txt
file_ls-1.0.1.dist-info/RECORD
