Metadata-Version: 2.1
Name: file-ls
Version: 1.0.1
Author: 唐旭东
Requires-Dist: natsort
